cheshirecat/__init__.py
cheshirecat-0.0.1.dist-info/LICENSE
cheshirecat-0.0.1.dist-info/METADATA
cheshirecat-0.0.1.dist-info/WHEEL
cheshirecat-0.0.1.dist-info/top_level.txt
cheshirecat-0.0.1.dist-info/RECORD
