Metadata-Version: 2.1
Name: cheshirecat
Version: 0.0.1
Summary: Prints the cheshire cat.
Author-email: ch35hireC4t <sim.teich@gmail.com>
Project-URL: Homepage, https://github.com/SimchaTeich/My_First_Python_PyPI_Package
Classifier: Programming Language :: Python :: 3
Classifier: License :: OSI Approved :: MIT License
Classifier: Operating System :: OS Independent
Requires-Python: >=3.9.7
License-File: LICENSE
